nonebot_plugin_warframe/__init__.py
nonebot_plugin_warframe/data_source.py
nonebot_plugin_warframe_test-0.0.3.dist-info/LICENSE
nonebot_plugin_warframe_test-0.0.3.dist-info/METADATA
nonebot_plugin_warframe_test-0.0.3.dist-info/WHEEL
nonebot_plugin_warframe_test-0.0.3.dist-info/top_level.txt
nonebot_plugin_warframe_test-0.0.3.dist-info/RECORD
